<?xml version="1.0" ?>
<Archtypes>

<Archtype id="15">Academic</Archtype>
<Archtype id="32">Commoner</Archtype>
<Archtype id="49">Knave</Archtype>
<Archtype id="66">Ranger</Archtype>
<Archtype id="83">Socialite</Archtype>
<Archtype id="100">Warrior</Archtype>

<Academic>
   <Trappings>Fine Clothing</Trappings>
   <Trappings>Coin Purse</Trappings>
   <Trappings>Loose Robes</Trappings>
   <Trappings>Leather Sandals/Soft Shoes</Trappings>
   <Trappings>Holy Symbol</Trappings>
   <Trappings>Writing Kit</Trappings>
   <Trappings>Shoulder Bag</Trappings>
   <Trappings>Smelling Salts</Trappings>
   <Trappings>Smelling Salts</Trappings>
   <Trappings>Smelling Salts</Trappings>
   <Trappings>Bottle of Leeches</Trappings>
   <Trappings>Black Lotus</Trappings>
   <Trappings>Dirk</Trappings>
   <Trappings>Cudgel/Staff/Throwing Knives</Trappings>

   <Profession name="8" value="Adherent" />
   <Profession name="16" value="Anchorite" />
   <Profession name="25" value="Antiquarian" />
   <Profession name="33" value="Apothecary" />
   <Profession name="41" value="Astrologer" />
   <Profession name="49" value="Diabolist" />
   <Profession name="58" value="Engineer" />
   <Profession name="67" value="Informer" />
   <Profession name="76" value="Investigator" />
   <Profession name="85" value="Monk" />
   <Profession name="92" value="Preacher" />
   <Profession name="100" value="Scribe" />
</Academic>

<Commoner>
   <Trappings>Simple Attire</Trappings>
   <Trappings>Warm Vest</Trappings>
   <Trappings>Bandages</Trappings>
   <Trappings>Bandages</Trappings>
   <Trappings>Bandages</Trappings>
   <Trappings>Ruck Sack</Trappings>
   <Trappings>Graveroot</Trappings>
   <Trappings>Heavy Boots</Trappings>
   <Trappings>Holy Symbol</Trappings>
   <Trappings>Shiv</Trappings>
   <Trappings>Shepherd's Sling/Splitting Maul/Threshing Flail</Trappings>

   <Profession name="8" value="Artisan" />
   <Profession name="16" value="Barber Surgeon" />
   <Profession name="25" value="Boartman" />
   <Profession name="33" value="Camp Follower" />
   <Profession name="41" value="Cheapjack" />
   <Profession name="49" value="Coachmaster" />
   <Profession name="58" value="Jailer" />
   <Profession name="67" value="Laborer" />
   <Profession name="76" value="Peasant" />
   <Profession name="85" value="Penitent" />
   <Profession name="92" value="Rat Catcher" />
   <Profession name="100" value="Servant" />
</Commoner>

<Knave>
   <Trapppings>Second-hand Attire/Dark Clothing/Tattered Rags/Garish Attire</Trapppings>
   <Trapppings>Soft Shoes</Trapppings>
   <Trapppings>Holy Symbol</Trapppings>
   <Trapppings>Gaff Bag</Trapppings>
   <Trapppings>Lock Picks</Trapppings>
   <Trapppings>Folkbane</Trapppings>
   <Trapppings>Antivenom</Trapppings>
   <Trapppings>Mantle</Trapppings>
   <Trapppings>Stiletto</Trapppings>
   <Trapppings>Blakjack/Garrote/Flintlock Pistol</Trapppings>

   <Profession name="8" value="Beggar" />
   <Profession name="16" value="Burglar" />
   <Profession name="25" value="Charlatan" />
   <Profession name="33" value="Footpad" />
   <Profession name="41" value="Gambler" />
   <Profession name="49" value="Graverobber" />
   <Profession name="58" value="Guttersnipe" />
   <Profession name="67" value="Highwayman" />
   <Profession name="76" value="Prostitute" />
   <Profession name="85" value="Smuggler" />
   <Profession name="92" value="Vagabond" />
   <Profession name="100" value="vigilante" />
</Knave>

   <Ranger>
      <Trapppings>Sturdy Traveling Cloths</Trapppings>
      <Trapppings>Fur Armor/Hide Armor</Trapppings>
      <Trapppings>Wilderness Cloak</Trapppings>
      <Trapppings>Heavy Boots</Trapppings>
      <Trapppings>Bullwhip</Trapppings>
      <Trapppings>Antivenom</Trapppings>
      <Trapppings>Wolfsbane</Trapppings>
      <Trapppings>Backpack</Trapppings>
      <Trapppings>Bedroll</Trapppings>
      <Trapppings>Animalbane</Trapppings>
      <Trapppings>Water Skin</Trapppings>
      <Trapppings>Torch</Trapppings>
      <Trapppings>Torch</Trapppings>
      <Trapppings>Torch</Trapppings>
      <Trapppings>Holy Symbol</Trapppings>
      <Trapppings>Survival Kit</Trapppings>
      <Trapppings>Fire-Hardened Spear/Hunting Bow/Woodsman's Axe</Trapppings>

      <Profession name="8" value="Animal Tamer" />
      <Profession name="16" value="Bailiff" />
      <Profession name="25" value="Bonepicker" />
      <Profession name="33" value="Bounty Hunter" />
      <Profession name="41" value="Gamekeeper" />
      <Profession name="49" value="Hedgewise" />
      <Profession name="58" value="Old Believer" />
      <Profession name="67" value="Outrider" />
      <Profession name="76" value="Pilgrim" />
      <Profession name="85" value="Reeve" />
      <Profession name="92" value="Slayer" />
      <Profession name="100" value="Trapper" />
   </Ranger>

   <Socialite>
      <Trapppings>Fashionable Clothing</Trapppings>
      <Trapppings>Fancy Shoes</Trapppings>
      <Trapppings>Foppish Hat</Trapppings>
      <Trapppings>Mantle</Trapppings>
      <Trapppings>Writting Kit</Trapppings>
      <Trapppings>Coin Purse</Trapppings>
      <Trapppings>Holy Symbol</Trapppings>
      <Trapppings>Knuckleduster</Trapppings>
      <Trapppings>Mandrake Root</Trapppings>
      <Trapppings>Laudanum</Trapppings>
      <Trapppings>Laudanum</Trapppings>
      <Trapppings>Laudanum</Trapppings>
      <Trapppings>Shoulder Bag</Trapppings>
      <Trapppings>Walking Cane</Trapppings>
      <Trapppings>Rapier/Throwing Knives</Trapppings>

      <Profession name="8" value="Anarchist" />
      <Profession name="16" value="Courtier" />
      <Profession name="25" value="Cultist" />
      <Profession name="33" value="Entertainer" />
      <Profession name="41" value="Envoy" />
      <Profession name="49" value="Fop" />
      <Profession name="58" value="Jester" />
      <Profession name="67" value="Provocateur" />
      <Profession name="76" value="Racketeer" />
      <Profession name="85" value="Raconteur" />
      <Profession name="92" value="Rake" />
      <Profession name="100" value="Valet" />
   </Socialite>

   <Warrior>
      <Trapppings>Military Attire</Trapppings>
      <Trapppings>Leather Armor</Trapppings>
      <Trapppings>Heavy Boots</Trapppings>
      <Trapppings>Wilderness Cloak</Trapppings>
      <Trapppings>Flask</Trapppings>
      <Trapppings>Lantern</Trapppings>
      <Trapppings>Oil Pot</Trapppings>
      <Trapppings>Fire-hardened Spear</Trapppings>
      <Trapppings>Quicksilver</Trapppings>
      <Trapppings>Tincture</Trapppings>
      <Trapppings>Red Cap Mushrooms</Trapppings>
      <Trapppings>Wooden Shield</Trapppings>
      <Trapppings>Rucksack</Trapppings>
      <Trapppings>Arbalest/Crossbow/Mortuary Sword/Pike</Trapppings>

      <Profession name="8" value="Berserker" />
      <Profession name="16" value="Bravo" />
      <Profession name="25" value="Buccaneer" />
      <Profession name="33" value="Dragoon" />
      <Profession name="41" value="Hedge Knight" />
      <Profession name="49" value="Man-At-Arms" />
      <Profession name="58" value="Militiaman" />
      <Profession name="67" value="Pit Fighter" />
      <Profession name="76" value="Pugilist" />
      <Profession name="85" value="Spellsword" />
      <Profession name="92" value="Squire" />
      <Profession name="100" value="Watchman" />
   </Warrior>

</Archtypes>
